uai_pre_import_transform_interface/__init__.py
uai_pre_import_transform_interface/pre_import_transform.py
uai_pre_import_transform_interface/py.typed
uai_pre_import_transform_interface-1.1.2.dist-info/LICENSE
uai_pre_import_transform_interface-1.1.2.dist-info/WHEEL
uai_pre_import_transform_interface-1.1.2.dist-info/METADATA
uai_pre_import_transform_interface-1.1.2.dist-info/RECORD
