Metadata-Version: 2.1
Name: uai-pre-import-transform-interface
Version: 1.1.2
Summary: 
License: MIT
Author: understand.ai
Author-email: postmaster@understand.ai
Requires-Python: >=3.8,<4.0
Classifier: License :: OSI Approved :: MIT License
Classifier: Programming Language :: Python :: 3
Classifier: Programming Language :: Python :: 3.8
Classifier: Programming Language :: Python :: 3.9
Classifier: Programming Language :: Python :: 3.10
Classifier: Programming Language :: Python :: 3.11
Requires-Dist: uai-uri-interface (>=0.1.0,<0.2.0)
